<?xml version='1.0' encoding='UTF-8'?>
<!DOCTYPE ManagedAttribute PUBLIC "sailpoint.dtd" "sailpoint.dtd">
<ManagedAttribute aggregated="true" attribute="Roles" displayName="ADH_BANK_IBAN" hash="e658060b0647d01525efbe8fb8319ce4dff8f2b7" lastRefresh="1658477548513" requestable="true" type="Group" value="ADH_BANK_IBAN">
  <ApplicationRef>
    <Reference class="sailpoint.object.Application" name="Test HR"/>
  </ApplicationRef>
  <Attributes>
    <Map>
      <entry key="Description" value="Abu Dhabi Bank role to inquire IBAN information"/>
      <entry key="sysDescriptions"/>
    </Map>
  </Attributes>
</ManagedAttribute>